release_bot/__init__.py
release_bot/__main__.py
release_bot/cli.py
release_bot/configuration.py
release_bot/exceptions.py
release_bot/git.py
release_bot/github.py
release_bot/new_pr.py
release_bot/new_release.py
release_bot/pypi.py
release_bot/releasebot.py
release_bot/utils.py
release_bot/version.py
release_bot/webhooks.py
release_bot-0.7.1.dist-info/LICENSE
release_bot-0.7.1.dist-info/METADATA
release_bot-0.7.1.dist-info/WHEEL
release_bot-0.7.1.dist-info/entry_points.txt
release_bot-0.7.1.dist-info/top_level.txt
release_bot-0.7.1.dist-info/RECORD
