Metadata-Version: 2.1
Name: release-bot
Version: 0.7.1
Summary: Automated releasing from GitHub repositories.
Home-page: https://github.com/user-cont/release-bot
Author: Red Hat
Author-email: user-cont-team@redhat.com
License: GPLv3+
Keywords: git,github,release,PyPI,packaging
Platform: UNKNOWN
Classifier: Development Status :: 4 - Beta
Classifier: Intended Audience :: Developers
Classifier: License :: OSI Approved :: GNU General Public License v3 or later (GPLv3+)
Classifier: Operating System :: POSIX :: Linux
Classifier: Programming Language :: Python :: 3
Classifier: Topic :: Software Development
Requires-Python: >=3.6
Requires-Dist: PyYAML
Requires-Dist: requests
Requires-Dist: semantic-version
Requires-Dist: twine
Requires-Dist: wheel
Requires-Dist: PyJWT
Requires-Dist: flask
